convolve/__init__.py
convolve_olivernormand-0.0.1.dist-info/LICENSE.txt
convolve_olivernormand-0.0.1.dist-info/METADATA
convolve_olivernormand-0.0.1.dist-info/WHEEL
convolve_olivernormand-0.0.1.dist-info/top_level.txt
convolve_olivernormand-0.0.1.dist-info/RECORD
